ortools_linearization/__init__.py
ortools_linearization/linearization.py
tests/__init__.py
tests/test_linearization.py
or_tools_linearization-0.1.1.dist-info/LICENSE
or_tools_linearization-0.1.1.dist-info/METADATA
or_tools_linearization-0.1.1.dist-info/WHEEL
or_tools_linearization-0.1.1.dist-info/top_level.txt
or_tools_linearization-0.1.1.dist-info/RECORD
